{
  "users": [
    {
      "id": "1",
      "username": "testuser",
      "address": {
        "city": "Test City",
        "street": "Test Street"
      },
      "password": "password"
    },
    {
      "username": "Ahmed",
      "address": {
        "city": "Assiut",
        "street": "Manqbad"
      },
      "password": "123",
      "confirmedPassword": "123",
      "id": "vMYubet-Z9E"
    },
    {
      "username": "Ahmed",
      "address": {
        "city": "Assiut",
        "street": "Manqbad"
      },
      "password": "123",
      "confirmedPassword": "123",
      "id": "AttCfMS9_sU"
    },
    {
      "username": "Ahmed",
      "address": {
        "city": "Assiut",
        "street": "Manqbad"
      },
      "password": "123",
      "confirmedPassword": "123",
      "id": "DqW8h1so2EI"
    },
    {
      "username": "Ahmed",
      "address": {
        "city": "dsafadf",
        "street": "dasf"
      },
      "password": "123",
      "confirmedPassword": "123",
      "id": "2zu877JBsVw"
    },
    {
      "username": "David",
      "address": {
        "city": "1",
        "street": "q"
      },
      "password": "123",
      "confirmedPassword": "123",
      "id": "8AggHU9AKnw"
    }
  ],
  "$schema": "./node_modules/json-server/schema.json"
}